metatoolkit/__init__.py
metatoolkit/audio.py
metatoolkit/cli.py
metatoolkit/core.py
metatoolkit/exceptions.py
metatoolkit/image.py
metatoolkit/video.py
metatoolkit-0.1.1.dist-info/entry_points.txt
metatoolkit-0.1.1.dist-info/LICENSE
metatoolkit-0.1.1.dist-info/METADATA
metatoolkit-0.1.1.dist-info/WHEEL
metatoolkit-0.1.1.dist-info/RECORD
