Metadata-Version: 2.3
Name: metatoolkit
Version: 0.1.1
Summary: A powerful Python library for processing metadata of images, videos, and audio files
License: MIT
Keywords: image,metadata,exif,watermark,video,audio
Author: Hmily
Requires-Python: >=3.10,<4.0
Classifier: License :: OSI Approved :: MIT License
Classifier: Programming Language :: Python :: 3
Classifier: Programming Language :: Python :: 3.10
Classifier: Programming Language :: Python :: 3.11
Classifier: Programming Language :: Python :: 3.12
Classifier: Programming Language :: Python :: 3.13
Requires-Dist: Pillow (>=9.5.0)
Requires-Dist: pyexiv2 (>=2.15.4)
Project-URL: Documentation, https://metatoolkit.readthedocs.io
Project-URL: Homepage, https://github.com/ihmily/metatoolkit
Project-URL: Source, https://github.com/ihmily/metatoolkit
